attrs2bin/__init__.py
attrs2bin/dequebuffer.py
attrs2bin/exceptions.py
attrs2bin/interfaces.py
attrs2bin/serializers.py
attrs2bin-0.0.1.dist-info/LICENSE
attrs2bin-0.0.1.dist-info/METADATA
attrs2bin-0.0.1.dist-info/WHEEL
attrs2bin-0.0.1.dist-info/top_level.txt
attrs2bin-0.0.1.dist-info/RECORD
