Metadata-Version: 2.1
Name: attrs2bin
Version: 0.0.1
Summary: Binary serializer for attrs-based classes
Home-page: https://github.com/fvicent/attrs2bin
Author: Francisco Vicent
Author-email: franciscovicent@outlook.com
License: UNKNOWN
Platform: UNKNOWN
Classifier: Programming Language :: Python :: 3
Classifier: License :: OSI Approved :: MIT License
Classifier: Operating System :: OS Independent
Classifier: Development Status :: 3 - Alpha
Classifier: Programming Language :: Rust
Requires-Python: >=3.6
Requires-Dist: zope.interface
Requires-Dist: zope.component
Requires-Dist: attrs
